<?xml version="1.0" encoding="UTF-8"?>
<mxGraphModel dx="946" dy="540" grid="1" gridSize="10" guides="1" tooltips="1" connect="1" arrows="1" fold="1" page="1" pageScale="1" pageWidth="850" pageHeight="1100" background="#ffffff" math="0" shadow="0"><root><mxCell id="0"/><mxCell id="1" parent="0"/><mxCell id="5717a064a35b69fd-5" value="Product Title" style="fillColor=none;strokeColor=none;html=1;fontSize=11;fontStyle=0;align=left;fontColor=#596780;fontStyle=1;fontSize=11" vertex="1" parent="1"><mxGeometry x="260" y="10" width="240" height="20" as="geometry"/></mxCell><mxCell id="5717a064a35b69fd-6" value="" style="rounded=1;arcSize=9;fillColor=#ffffff;align=left;spacingLeft=5;strokeColor=#4C9AFF;html=1;strokeWidth=2;fontColor=#000000;fontSize=12" vertex="1" parent="1"><mxGeometry x="260" y="35" width="290" height="33" as="geometry"/></mxCell><mxCell id="5717a064a35b69fd-8" value="Select Category" style="html=1;shadow=0;dashed=0;shape=mxgraph.bootstrap.rrect;align=center;rSize=5;strokeColor=#000000;spacingRight=10;fontSize=16;gradientDirection=north;whiteSpace=wrap;fillColor=none;" vertex="1" parent="1"><mxGeometry x="260" y="90" width="290" height="40" as="geometry"/></mxCell><mxCell id="5717a064a35b69fd-9" value="" style="shape=triangle;direction=south;fillColor=#000000;strokeColor=none;perimeter=none;" vertex="1" parent="5717a064a35b69fd-8"><mxGeometry x="1" y="0.5" width="10" height="5" relative="1" as="geometry"><mxPoint x="-20" y="-2.5" as="offset"/></mxGeometry></mxCell><mxCell id="5717a064a35b69fd-11" value="Select Mart" style="html=1;shadow=0;dashed=0;shape=mxgraph.bootstrap.rrect;align=center;rSize=5;strokeColor=#000000;spacingRight=10;fontSize=16;gradientDirection=north;whiteSpace=wrap;fillColor=none;" vertex="1" parent="1"><mxGeometry x="260" y="160" width="290" height="40" as="geometry"/></mxCell><mxCell id="5717a064a35b69fd-12" value="" style="shape=triangle;direction=south;fillColor=#000000;strokeColor=none;perimeter=none;" vertex="1" parent="5717a064a35b69fd-11"><mxGeometry x="1" y="0.5" width="10" height="5" relative="1" as="geometry"><mxPoint x="-20" y="-2.5" as="offset"/></mxGeometry></mxCell><mxCell id="5717a064a35b69fd-13" value="" style="rounded=1;arcSize=9;fillColor=#ffffff;align=left;spacingLeft=5;strokeColor=#4C9AFF;html=1;strokeWidth=2;fontColor=#000000;fontSize=12" vertex="1" parent="1"><mxGeometry x="262" y="245" width="290" height="33" as="geometry"/></mxCell><mxCell id="5717a064a35b69fd-14" value="Price" style="fillColor=none;strokeColor=none;html=1;fontSize=11;fontStyle=0;align=left;fontColor=#596780;fontStyle=1;fontSize=11" vertex="1" parent="1"><mxGeometry x="260" y="220" width="240" height="20" as="geometry"/></mxCell><mxCell id="5717a064a35b69fd-16" value="&lt;font style=&quot;font-size: 14px&quot;&gt;Product Description&lt;/font&gt;" style="strokeWidth=1;html=1;shadow=0;dashed=0;shape=mxgraph.ios.iTextInput;strokeColor=#444444;fontColor=#000000;buttonText=;fontSize=8;fillColor=#ffffff;whiteSpace=wrap;align=left;" vertex="1" parent="1"><mxGeometry x="262" y="300" width="288" height="90" as="geometry"/></mxCell><mxCell id="5717a064a35b69fd-19" value="" style="shape=image;html=1;verticalAlign=top;verticalLabelPosition=bottom;labelBackgroundColor=#ffffff;imageAspect=0;aspect=fixed;image=https://cdn2.iconfinder.com/data/icons/snipicons/500/upload-128.png;fillColor=none;gradientColor=#ffffff;fontSize=17;" vertex="1" parent="1"><mxGeometry x="262" y="410" width="40" height="40" as="geometry"/></mxCell><mxCell id="5717a064a35b69fd-20" value="Upload Image" style="text;html=1;strokeColor=none;fillColor=none;align=center;verticalAlign=middle;whiteSpace=wrap;fontSize=17;" vertex="1" parent="1"><mxGeometry x="320" y="420" width="120" height="20" as="geometry"/></mxCell><mxCell id="5717a064a35b69fd-21" value="&lt;font style=&quot;font-size: 14px&quot;&gt;Insert &amp;nbsp;Item&lt;/font&gt;" style="strokeWidth=1;html=1;shadow=0;dashed=0;shape=mxgraph.ios.iButton;strokeColor=#444444;fontColor=#ffffff;buttonText=;fontSize=8;fillColor=#dddddd;fillColor2=#3D5565;whiteSpace=wrap;align=center;" vertex="1" parent="1"><mxGeometry x="350" y="460" width="100" height="30" as="geometry"/></mxCell><mxCell id="5717a064a35b69fd-23" value="&lt;font style=&quot;font-size: 14px&quot;&gt;+ Add More Items&lt;/font&gt;" style="strokeWidth=1;html=1;shadow=0;dashed=0;shape=mxgraph.ios.iButton;strokeColor=#444444;fontColor=#ffffff;buttonText=;fontSize=8;fillColor=#dddddd;fillColor2=#3D5565;whiteSpace=wrap;align=center;" vertex="1" parent="1"><mxGeometry x="350" y="520" width="100" height="30" as="geometry"/></mxCell><mxCell id="5717a064a35b69fd-24" value="" style="strokeWidth=2;html=1;shape=mxgraph.flowchart.annotation_2;align=left;fillColor=none;gradientColor=#ffffff;fontSize=17;" vertex="1" parent="1"><mxGeometry x="460" y="478" width="342" height="115" as="geometry"/></mxCell><mxCell id="5717a064a35b69fd-25" value="After clicking this whole form opens again and this button will disappear" style="text;html=1;strokeColor=none;fillColor=none;align=center;verticalAlign=middle;whiteSpace=wrap;fontSize=17;" vertex="1" parent="1"><mxGeometry x="670" y="505" width="150" height="70" as="geometry"/></mxCell><mxCell id="5717a064a35b69fd-26" value="Product Title" style="fillColor=none;strokeColor=none;html=1;fontSize=11;fontStyle=0;align=left;fontColor=#596780;fontStyle=1;fontSize=11" vertex="1" parent="1"><mxGeometry x="218" y="565" width="240" height="20" as="geometry"/></mxCell><mxCell id="5717a064a35b69fd-27" value="" style="rounded=1;arcSize=9;fillColor=#ffffff;align=left;spacingLeft=5;strokeColor=#4C9AFF;html=1;strokeWidth=2;fontColor=#000000;fontSize=12" vertex="1" parent="1"><mxGeometry x="254" y="585" width="290" height="33" as="geometry"/></mxCell><mxCell id="5717a064a35b69fd-28" value="Select Category" style="html=1;shadow=0;dashed=0;shape=mxgraph.bootstrap.rrect;align=center;rSize=5;strokeColor=#000000;spacingRight=10;fontSize=16;gradientDirection=north;whiteSpace=wrap;fillColor=none;" vertex="1" parent="1"><mxGeometry x="254" y="640" width="290" height="40" as="geometry"/></mxCell><mxCell id="5717a064a35b69fd-29" value="" style="shape=triangle;direction=south;fillColor=#000000;strokeColor=none;perimeter=none;" vertex="1" parent="5717a064a35b69fd-28"><mxGeometry x="1" y="0.5" width="10" height="5" relative="1" as="geometry"><mxPoint x="-20" y="-2.5" as="offset"/></mxGeometry></mxCell><mxCell id="5717a064a35b69fd-30" value="Select Mart" style="html=1;shadow=0;dashed=0;shape=mxgraph.bootstrap.rrect;align=center;rSize=5;strokeColor=#000000;spacingRight=10;fontSize=16;gradientDirection=north;whiteSpace=wrap;fillColor=none;" vertex="1" parent="1"><mxGeometry x="254" y="710" width="290" height="40" as="geometry"/></mxCell><mxCell id="5717a064a35b69fd-31" value="" style="shape=triangle;direction=south;fillColor=#000000;strokeColor=none;perimeter=none;" vertex="1" parent="5717a064a35b69fd-30"><mxGeometry x="1" y="0.5" width="10" height="5" relative="1" as="geometry"><mxPoint x="-20" y="-2.5" as="offset"/></mxGeometry></mxCell><mxCell id="5717a064a35b69fd-32" value="" style="rounded=1;arcSize=9;fillColor=#ffffff;align=left;spacingLeft=5;strokeColor=#4C9AFF;html=1;strokeWidth=2;fontColor=#000000;fontSize=12" vertex="1" parent="1"><mxGeometry x="256" y="795" width="290" height="33" as="geometry"/></mxCell><mxCell id="5717a064a35b69fd-33" value="Price" style="fillColor=none;strokeColor=none;html=1;fontSize=11;fontStyle=0;align=left;fontColor=#596780;fontStyle=1;fontSize=11" vertex="1" parent="1"><mxGeometry x="254" y="770" width="240" height="20" as="geometry"/></mxCell><mxCell id="5717a064a35b69fd-34" value="&lt;font style=&quot;font-size: 14px&quot;&gt;Product Description&lt;/font&gt;" style="strokeWidth=1;html=1;shadow=0;dashed=0;shape=mxgraph.ios.iTextInput;strokeColor=#444444;fontColor=#000000;buttonText=;fontSize=8;fillColor=#ffffff;whiteSpace=wrap;align=left;" vertex="1" parent="1"><mxGeometry x="256" y="850" width="288" height="90" as="geometry"/></mxCell><mxCell id="5717a064a35b69fd-35" value="" style="shape=image;html=1;verticalAlign=top;verticalLabelPosition=bottom;labelBackgroundColor=#ffffff;imageAspect=0;aspect=fixed;image=https://cdn2.iconfinder.com/data/icons/snipicons/500/upload-128.png;fillColor=none;gradientColor=#ffffff;fontSize=17;" vertex="1" parent="1"><mxGeometry x="256" y="960" width="40" height="40" as="geometry"/></mxCell><mxCell id="5717a064a35b69fd-36" value="Upload Image" style="text;html=1;strokeColor=none;fillColor=none;align=center;verticalAlign=middle;whiteSpace=wrap;fontSize=17;" vertex="1" parent="1"><mxGeometry x="314" y="970" width="120" height="20" as="geometry"/></mxCell><mxCell id="5717a064a35b69fd-37" value="&lt;font style=&quot;font-size: 14px&quot;&gt;Insert &amp;nbsp;Item&lt;/font&gt;" style="strokeWidth=1;html=1;shadow=0;dashed=0;shape=mxgraph.ios.iButton;strokeColor=#444444;fontColor=#ffffff;buttonText=;fontSize=8;fillColor=#dddddd;fillColor2=#3D5565;whiteSpace=wrap;align=center;" vertex="1" parent="1"><mxGeometry x="344" y="1010" width="100" height="30" as="geometry"/></mxCell><mxCell id="5717a064a35b69fd-38" value="&lt;font style=&quot;font-size: 14px&quot;&gt;+ Add More Items&lt;/font&gt;" style="strokeWidth=1;html=1;shadow=0;dashed=0;shape=mxgraph.ios.iButton;strokeColor=#444444;fontColor=#ffffff;buttonText=;fontSize=8;fillColor=#dddddd;fillColor2=#3D5565;whiteSpace=wrap;align=center;" vertex="1" parent="1"><mxGeometry x="344" y="1055" width="100" height="30" as="geometry"/></mxCell></root></mxGraphModel>